{
  "id": "spec-match-4",
  "tournamentId": "classic-tournament",
  "player1Id": "test-player-1",
  "player2Id": "test-player-2",
  "player1DeckId": "classic-fire-starter-deck",
  "player2DeckId": "classic-water-starter-deck",
  "state": "PLAYER_TURN",
  "currentPlayer": "PLAYER2",
  "firstPlayer": "PLAYER2",
  "player1HasDrawnValidHand": true,
  "player2HasDrawnValidHand": true,
  "player1HasSetPrizeCards": true,
  "player2HasSetPrizeCards": true,
  "player1ReadyToStart": true,
  "player2ReadyToStart": true,
  "player1HasConfirmedFirstPlayer": true,
  "player2HasConfirmedFirstPlayer": true,
  "player1HasApprovedMatch": true,
  "player2HasApprovedMatch": true,
  "createdAt": "2025-12-11T19:15:09.204Z",
  "updatedAt": "2025-12-11T19:15:10.964Z",
  "startedAt": null,
  "endedAt": null,
  "winnerId": null,
  "result": null,
  "winCondition": null,
  "cancellationReason": null,
  "gameState": {
    "player1State": {
      "deck": [
        "pokemon-base-set-v1.0-energy-retrieval--83",
        "pokemon-base-set-v1.0-fire-energy--99",
        "pokemon-base-set-v1.0-vulpix--70",
        "pokemon-base-set-v1.0-switch--96",
        "pokemon-base-set-v1.0-fire-energy--99",
        "pokemon-base-set-v1.0-fire-energy--99",
        "pokemon-base-set-v1.0-fire-energy--99",
        "pokemon-base-set-v1.0-bill--92",
        "pokemon-base-set-v1.0-fire-energy--99",
        "pokemon-base-set-v1.0-fire-energy--99",
        "pokemon-base-set-v1.0-fire-energy--99",
        "pokemon-base-set-v1.0-fire-energy--99",
        "pokemon-base-set-v1.0-bill--92",
        "pokemon-base-set-v1.0-energy-removal--93",
        "pokemon-base-set-v1.0-charizard--4",
        "pokemon-base-set-v1.0-fire-energy--99",
        "pokemon-base-set-v1.0-charmeleon--24",
        "pokemon-base-set-v1.0-fire-energy--99",
        "pokemon-base-set-v1.0-vulpix--70",
        "pokemon-base-set-v1.0-potion--90",
        "pokemon-base-set-v1.0-fire-energy--99",
        "pokemon-base-set-v1.0-fire-energy--99",
        "pokemon-base-set-v1.0-bill--92",
        "pokemon-base-set-v1.0-potion--90",
        "pokemon-base-set-v1.0-potion--90",
        "pokemon-base-set-v1.0-magmar--36",
        "pokemon-base-set-v1.0-gust-of-wind--94",
        "pokemon-base-set-v1.0-pokemon-breeder--78",
        "pokemon-base-set-v1.0-charmander--48",
        "pokemon-base-set-v1.0-fire-energy--99",
        "pokemon-base-set-v1.0-magmar--36",
        "pokemon-base-set-v1.0-bill--92",
        "pokemon-base-set-v1.0-fire-energy--99",
        "pokemon-base-set-v1.0-fire-energy--99",
        "pokemon-base-set-v1.0-growlithe--28",
        "pokemon-base-set-v1.0-fire-energy--99",
        "pokemon-base-set-v1.0-ponyta--62",
        "pokemon-base-set-v1.0-energy-removal--93",
        "pokemon-base-set-v1.0-charmander--48",
        "pokemon-base-set-v1.0-fire-energy--99",
        "pokemon-base-set-v1.0-fire-energy--99",
        "pokemon-base-set-v1.0-fire-energy--99",
        "pokemon-base-set-v1.0-switch--96",
        "pokemon-base-set-v1.0-ponyta--62",
        "pokemon-base-set-v1.0-fire-energy--99",
        "pokemon-base-set-v1.0-energy-retrieval--83",
        "pokemon-base-set-v1.0-fire-energy--99"
      ],
      "hand": [
        "pokemon-base-set-v1.0-fire-energy--99",
        "pokemon-base-set-v1.0-fire-energy--99",
        "pokemon-base-set-v1.0-fire-energy--99",
        "pokemon-base-set-v1.0-fire-energy--99",
        "pokemon-base-set-v1.0-gust-of-wind--94",
        "pokemon-base-set-v1.0-charmander--48"
      ],
      "activePokemon": {
        "instanceId": "a48c7137-74e2-427a-aa8e-efbd6a3fb6b3",
        "cardId": "pokemon-base-set-v1.0-charmeleon--24",
        "position": "ACTIVE",
        "currentHp": 80,
        "maxHp": 80,
        "attachedEnergy": [],
        "statusEffect": "NONE",
        "damageCounters": 0,
        "evolutionChain": []
      },
      "bench": [],
      "prizeCards": [
        "pokemon-base-set-v1.0-charmander--48",
        "pokemon-base-set-v1.0-ponyta--62",
        "pokemon-base-set-v1.0-pokemon-breeder--78",
        "pokemon-base-set-v1.0-fire-energy--99",
        "pokemon-base-set-v1.0-growlithe--28",
        "pokemon-base-set-v1.0-fire-energy--99"
      ],
      "discardPile": [],
      "hasAttachedEnergyThisTurn": false
    },
    "player2State": {
      "deck": [
        "pokemon-base-set-v1.0-starmie--66",
        "pokemon-base-set-v1.0-poliwhirl--40",
        "pokemon-base-set-v1.0-water-energy--103",
        "pokemon-base-set-v1.0-potion--90",
        "pokemon-base-set-v1.0-water-energy--103",
        "pokemon-base-set-v1.0-squirtle--65",
        "pokemon-base-set-v1.0-water-energy--103",
        "pokemon-base-set-v1.0-water-energy--103",
        "pokemon-base-set-v1.0-water-energy--103",
        "pokemon-base-set-v1.0-water-energy--103",
        "pokemon-base-set-v1.0-bill--92",
        "pokemon-base-set-v1.0-water-energy--103",
        "pokemon-base-set-v1.0-water-energy--103",
        "pokemon-base-set-v1.0-pokemon-breeder--78",
        "pokemon-base-set-v1.0-water-energy--103",
        "pokemon-base-set-v1.0-water-energy--103",
        "pokemon-base-set-v1.0-energy-removal--93",
        "pokemon-base-set-v1.0-poliwag--39",
        "pokemon-base-set-v1.0-potion--90",
        "pokemon-base-set-v1.0-energy-retrieval--83",
        "pokemon-base-set-v1.0-seel--43",
        "pokemon-base-set-v1.0-potion--90",
        "pokemon-base-set-v1.0-seel--43",
        "pokemon-base-set-v1.0-switch--96",
        "pokemon-base-set-v1.0-wartortle--44",
        "pokemon-base-set-v1.0-water-energy--103",
        "pokemon-base-set-v1.0-water-energy--103",
        "pokemon-base-set-v1.0-gust-of-wind--94",
        "pokemon-base-set-v1.0-blastoise--2",
        "pokemon-base-set-v1.0-water-energy--103",
        "pokemon-base-set-v1.0-bill--92",
        "pokemon-base-set-v1.0-wartortle--44",
        "pokemon-base-set-v1.0-water-energy--103",
        "pokemon-base-set-v1.0-poliwag--39",
        "pokemon-base-set-v1.0-pokemon-breeder--78",
        "pokemon-base-set-v1.0-water-energy--103",
        "pokemon-base-set-v1.0-water-energy--103",
        "pokemon-base-set-v1.0-water-energy--103",
        "pokemon-base-set-v1.0-squirtle--65",
        "pokemon-base-set-v1.0-water-energy--103",
        "pokemon-base-set-v1.0-magikarp--35",
        "pokemon-base-set-v1.0-water-energy--103",
        "pokemon-base-set-v1.0-poliwhirl--40",
        "pokemon-base-set-v1.0-energy-retrieval--83",
        "pokemon-base-set-v1.0-poliwrath--13",
        "pokemon-base-set-v1.0-squirtle--65"
      ],
      "hand": [
        "pokemon-base-set-v1.0-switch--96",
        "pokemon-base-set-v1.0-water-energy--103",
        "pokemon-base-set-v1.0-starmie--66",
        "pokemon-base-set-v1.0-energy-removal--93",
        "pokemon-base-set-v1.0-gust-of-wind--94",
        "pokemon-base-set-v1.0-magikarp--35",
        "pokemon-base-set-v1.0-water-energy--103"
      ],
      "activePokemon": {
        "instanceId": "a31d242e-ebcb-4f7b-9176-0b65e632398c",
        "cardId": "pokemon-base-set-v1.0-bill--92",
        "position": "ACTIVE",
        "currentHp": 100,
        "maxHp": 100,
        "attachedEnergy": [],
        "statusEffect": "NONE",
        "damageCounters": 0,
        "evolutionChain": []
      },
      "bench": [],
      "prizeCards": [
        "pokemon-base-set-v1.0-water-energy--103",
        "pokemon-base-set-v1.0-seel--43",
        "pokemon-base-set-v1.0-poliwag--39",
        "pokemon-base-set-v1.0-bill--92",
        "pokemon-base-set-v1.0-water-energy--103",
        "pokemon-base-set-v1.0-squirtle--65"
      ],
      "discardPile": [],
      "hasAttachedEnergyThisTurn": false
    },
    "turnNumber": 1,
    "phase": "MAIN_PHASE",
    "currentPlayer": "PLAYER2",
    "lastAction": {
      "actionId": "b4f89eb1-8aa8-45e3-853a-cf1634e80e38",
      "playerId": "PLAYER2",
      "actionType": "DRAW_CARD",
      "timestamp": "2025-12-11T19:15:10.964Z",
      "actionData": {}
    },
    "actionHistory": [
      {
        "actionId": "b4f89eb1-8aa8-45e3-853a-cf1634e80e38",
        "playerId": "PLAYER2",
        "actionType": "DRAW_CARD",
        "timestamp": "2025-12-11T19:15:10.964Z",
        "actionData": {}
      }
    ],
    "coinFlipState": null,
    "abilityUsageThisTurn": {
      "PLAYER1": [],
      "PLAYER2": []
    }
  }
}